polardb_postgresql_mcp_server/__init__.py
polardb_postgresql_mcp_server/server.py
polardb_postgresql_mcp_server-1.1.0.dist-info/METADATA
polardb_postgresql_mcp_server-1.1.0.dist-info/WHEEL
polardb_postgresql_mcp_server-1.1.0.dist-info/entry_points.txt
polardb_postgresql_mcp_server-1.1.0.dist-info/top_level.txt
polardb_postgresql_mcp_server-1.1.0.dist-info/RECORD
