Metadata-Version: 2.4
Name: polardb-postgresql-mcp-server
Version: 1.1.0
Summary: Add your description here
Requires-Python: >=3.12
Requires-Dist: mcp[cli]>=1.6.0
Requires-Dist: psycopg>=3.1.0
Requires-Dist: sqlparse>=0.4.4
